Metadata-Version: 2.4
Name: anonypyx
Version: 0.2.11
Summary: Anonymisation library for python, fork of anonypy
Author: questforwisdom, glassonion1
License: MIT License
Project-URL: Homepage, https://github.com/questforwisdom/anonypyx
Keywords: k-anonymity,l-diversity,t-closeness,anonymization,mondrian,microaggregation,mdav,ksame
Classifier: License :: OSI Approved :: MIT License
Classifier: Programming Language :: Python
Classifier: Programming Language :: Python :: 3
Classifier: Operating System :: OS Independent
Classifier: Development Status :: 4 - Beta
Classifier: Intended Audience :: Science/Research
Requires-Python: >=3.9
License-File: LICENSE
Requires-Dist: pandas>=1.5.0
Requires-Dist: numpy>=1.21.3
Requires-Dist: scikit-learn>=1.0.1
Requires-Dist: scipy>=1.11.3
Provides-Extra: dev
Requires-Dist: pytest; extra == "dev"
Dynamic: license-file
